odoo/addons/shopinvader_payment_adyen/README.rst
odoo/addons/shopinvader_payment_adyen/__init__.py
odoo/addons/shopinvader_payment_adyen/__manifest__.py
odoo/addons/shopinvader_payment_adyen/components/__init__.py
odoo/addons/shopinvader_payment_adyen/components/payment_transaction_event_listener.py
odoo/addons/shopinvader_payment_adyen/demo/payment_demo.xml
odoo/addons/shopinvader_payment_adyen/i18n/shopinvader_payment_adyen.pot
odoo/addons/shopinvader_payment_adyen/readme/CONTRIBUTORS.rst
odoo/addons/shopinvader_payment_adyen/readme/DESCRIPTION.rst
odoo/addons/shopinvader_payment_adyen/services/__init__.py
odoo/addons/shopinvader_payment_adyen/services/payment_adyen.py
odoo/addons/shopinvader_payment_adyen/static/description/index.html
odoo/addons/shopinvader_payment_adyen/tests/__init__.py
odoo/addons/shopinvader_payment_adyen/tests/common.py
odoo/addons/shopinvader_payment_adyen/tests/test_payment_adyen.py
odoo14_addon_shopinvader_payment_adyen-14.0.1.0.2.dist-info/METADATA
odoo14_addon_shopinvader_payment_adyen-14.0.1.0.2.dist-info/WHEEL
odoo14_addon_shopinvader_payment_adyen-14.0.1.0.2.dist-info/top_level.txt
odoo14_addon_shopinvader_payment_adyen-14.0.1.0.2.dist-info/RECORD
